{"data_mtime":1784664384,"dep_lines":[1,2,3,4,5,6,7,8,9,1],"dep_prios":[10,10,5,5,5,5,5,5,5,5],"dependencies":["collections","sys","typing_extensions","_collections_abc","_typeshed","abc","contextlib","re","types","builtins"],"hash":"a9cef16479ed5b0a9aa32414beb5e6208809cb5091e8d1e638321ce87126e5e6","id":"typing","ignore_all":true,"interface_hash":"da5c151d415e21ea06ad71bcf01bbd2ffd3748f8cd92d3ee6b5afc9588b73304","mtime":1784664355,"options":{"allow_redefinition":false,"allow_untyped_globals":false,"always_false":[],"always_true":[],"bazel":false,"check_untyped_defs":true,"disable_bytearray_promotion":false,"disable_error_code":[],"disable_memoryview_promotion":false,"disabled_error_codes":[],"disallow_any_decorated":false,"disallow_any_explicit":false,"disallow_any_expr":false,"disallow_any_generics":true,"disallow_any_unimported":false,"disallow_incomplete_defs":true,"disallow_subclassing_any":true,"disallow_untyped_calls":true,"disallow_untyped_decorators":true,"disallow_untyped_defs":true,"enable_error_code":[],"enabled_error_codes":[],"extra_checks":true,"follow_imports":"normal","follow_imports_for_stubs":false,"ignore_errors":false,"ignore_missing_imports":true,"implicit_optional":false,"implicit_reexport":false,"local_partial_types":false,"mypyc":false,"old_type_inference":false,"platform":"linux","plugins":["numpy.typing.mypy_plugin"],"strict_concatenate":false,"strict_equality":true,"strict_optional":true,"warn_no_return":true,"warn_return_any":true,"warn_unreachable":false,"warn_unused_ignores":true},"path":"/home/jules/.cache/pypoetry/virtualenvs/clintrials-9TtSrW0h-py3.12/lib/python3.12/site-packages/mypy/typeshed/stdlib/typing.pyi","plugin_data":null,"size":34350,"suppressed":[],"version_id":"1.8.0"}